Metadata-Version: 2.1
Name: timm
Version: 1.0.23
Summary: PyTorch Image Models
Keywords: pytorch,image-classification
Author-Email: Ross Wightman <ross@huggingface.co>
License: Apache-2.0
Classifier: Development Status :: 5 - Production/Stable
Classifier: Intended Audience :: Education
Classifier: Intended Audience :: Science/Research
Classifier: License :: OSI Approved :: Apache Software License
Classifier: Programming Language :: Python :: 3.8
Classifier: Programming Language :: Python :: 3.9
Classifier: Programming Language :: Python :: 3.10
Classifier: Programming Language :: Python :: 3.11
Classifier: Programming Language :: Python :: 3.12
Classifier: Topic :: Scientific/Engineering
Classifier: Topic :: Scientific/Engineering :: Artificial Intelligence
Classifier: Topic :: Software Development
Classifier: Topic :: Software Development :: Libraries
Classifier: Topic :: Software Development :: Libraries :: Python Modules
Project-URL: homepage, https://github.com/huggingface/pytorch-image-models
Project-URL: documentation, https://huggingface.co/docs/timm/en/index
Project-URL: repository, https://github.com/huggingface/pytorch-image-models
Requires-Python: >=3.8
Requires-Dist: torch
Requires-Dist: torchvision
Requires-Dist: pyyaml
Requires-Dist: huggingface_hub
Requires-Dist: safetensors
